mockpy/__init__.py
mockpy/mockpy.py
mockpy/data/__init__.py
mockpy/data/locales/__init__.py
mockpy/data/locales/en_US.json
mockpy/data/locales/tr_TR.json
python_mockpy-1.0.dist-info/LICENSE.md
python_mockpy-1.0.dist-info/METADATA
python_mockpy-1.0.dist-info/WHEEL
python_mockpy-1.0.dist-info/top_level.txt
python_mockpy-1.0.dist-info/RECORD
