Metadata-Version: 2.2
Name: python-mockpy
Version: 1.0
Summary: Comprehensive realistic data generation library for testing and development
Home-page: https://github.com/burakozcn01/mockpy
Author: Reloading
Author-email: reloading001@hotmail.com
Project-URL: Bug Reports, https://github.com/burakozcn01/mockpy/issues
Project-URL: Source, https://github.com/burakozcn01/mockpy
Keywords: mock,fake,data,testing,development,faker,generator,test data,random data,dummy data,sample data
Classifier: Development Status :: 4 - Beta
Classifier: Intended Audience :: Developers
Classifier: License :: OSI Approved :: MIT License
Classifier: Programming Language :: Python :: 3
Classifier: Programming Language :: Python :: 3.7
Classifier: Programming Language :: Python :: 3.8
Classifier: Programming Language :: Python :: 3.9
Classifier: Programming Language :: Python :: 3.10
Classifier: Programming Language :: Python :: 3.11
Classifier: Programming Language :: Python :: 3.12
Classifier: Programming Language :: Python :: 3.13
Classifier: Programming Language :: Python :: Implementation :: CPython
Classifier: Programming Language :: Python :: Implementation :: PyPy
Classifier: Topic :: Software Development :: Testing
Classifier: Topic :: Software Development :: Libraries :: Python Modules
Requires-Python: >=3.7
License-File: LICENSE.md
Provides-Extra: full
Requires-Dist: translators; extra == "full"
Requires-Dist: jsonschema; extra == "full"
Requires-Dist: django; extra == "full"
Requires-Dist: flask; extra == "full"
Requires-Dist: sqlalchemy; extra == "full"
Requires-Dist: pydantic; extra == "full"
Requires-Dist: numpy; extra == "full"
Provides-Extra: translate
Requires-Dist: translators; extra == "translate"
Provides-Extra: jsonschema
Requires-Dist: jsonschema; extra == "jsonschema"
Provides-Extra: django
Requires-Dist: django; extra == "django"
Provides-Extra: flask
Requires-Dist: flask; extra == "flask"
Provides-Extra: sqlalchemy
Requires-Dist: sqlalchemy; extra == "sqlalchemy"
Provides-Extra: fastapi
Requires-Dist: fastapi; extra == "fastapi"
Requires-Dist: pydantic; extra == "fastapi"
Provides-Extra: dev
Requires-Dist: pytest; extra == "dev"
Requires-Dist: pytest-cov; extra == "dev"
Requires-Dist: black; extra == "dev"
Requires-Dist: isort; extra == "dev"
Requires-Dist: flake8; extra == "dev"
Requires-Dist: pylint; extra == "dev"
Provides-Extra: performance
Requires-Dist: numpy; extra == "performance"
Dynamic: author
Dynamic: author-email
Dynamic: classifier
Dynamic: description
Dynamic: description-content-type
Dynamic: home-page
Dynamic: keywords
Dynamic: project-url
Dynamic: provides-extra
Dynamic: requires-python
Dynamic: summary
